LICENSE.txt
MANIFEST.in
README.md
setup.cfg
setup.py
exactonline/__init__.py
exactonline/api.py
exactonline/authhandler.py
exactonline/cachehandler.py
exactonline/config.py
exactonline/utils.py
exactonline/cache/__init__.py
exactonline/constants/constants.py
exactonline/constants/errors.py
exactonline/endpoints/__init__.py
exactonline/endpoints/accounts.py
exactonline/endpoints/base.py
exactonline/endpoints/contacts.py
exactonline/endpoints/documents.py
exactonline/endpoints/glaccounts.py
exactonline/endpoints/journals.py
exactonline/endpoints/salesentries.py
exactonline/endpoints/vatcodes.py
exactonline/models/__init__.py
exactonline/models/accounts.py
exactonline/models/base.py
exactonline/models/contacts.py
exactonline/models/documents.py
exactonline/models/errors.py
exactonline/models/glaccounts.py
exactonline/models/journals.py
exactonline/models/salesentries.py
exactonline/models/vat.py
python_exact_online.egg-info/PKG-INFO
python_exact_online.egg-info/SOURCES.txt
python_exact_online.egg-info/dependency_links.txt
python_exact_online.egg-info/requires.txt
python_exact_online.egg-info/top_level.txt