Metadata-Version: 2.1
Name: python-exact-online
Version: 0.2.0
Summary: Basic wrapper for the Exact Online REST API (v1)
Home-page: https://github.com/alexanderlhsglobal/python-exact-online
Author: Alexander Schillemans
Author-email: alexander.schillemans@lhs.global
License: GPL-3.0-or-later
Download-URL: https://github.com/alexanderlhsglobal/python-exact-online/archive/refs/tags/0.2.0.tar.gz
Keywords: exact,exact online,api
Platform: UNKNOWN
Classifier: Development Status :: 3 - Alpha
Classifier: Intended Audience :: Developers
Classifier: Topic :: Software Development :: Build Tools
Classifier: License :: OSI Approved :: GNU General Public License v3 or later (GPLv3+)
Classifier: Programming Language :: Python :: 3.6
License-File: LICENSE.txt
